{
  "homepage": "Hé nhô",
  "welcome": "BuyMore - Where you find the harmony between quality and great value. Wellcome! ",
  "welcomeLogin":"Wellcome",
  "brower": "Browse All Categories",
  "login": "Login",
  "account": "Account",
  "profile": "Profile",
  "signout": "Sign Out",
  "selectAll": "Select All",
  "goiy": "Recommended products for you",
  "Save": "Save",
  "prodNew": "Latest produc",
  "like": "You may also like",
  "viewed": "Recently viewed products",
  "maxProduct": "The maximum number of products is",
  "cart": "Your shopping cart",
  "product": "Product",
  "price": "Price",
  "quantity": "Quantity",
  "total": "Total",
  "delete": "Delete",
  "like Product": "Similar products",
  "outOfStock": "Out of stock",
  "backHome": "Back Home",
  "bill": "Summary",
  "totalProduct": "Total number of products",
  "totalPrice": "Amount to Pay",
  "discount": "Discount",
  "pay": "Pay",
  "oldPrice": "Old price",
  "buy": "BUY",
  "addCart": "ADD TO CART",
  "inforPr": "View information about the product",
  "desc": "Related articles",
  "config": "Configuration information",
  "rating": "Rating",
  "comment": "Add comment",
  "review": "Add Review",
  "related": "Related products",
  "ourInfor": "Our contact information",
  "contact": "Contact",
  "notEmpty": "Cannot be empty",
   "addAddressfail": "Adding new address failed",
   "cartEmpty":"You have not selected any products!!!",
   "deleteItemFailed": "Delete Items Failed",
   "correcInfor": "Please enter correct information",
   "checkAgain": "Please check the information again",
   "plsLogin": "Please log in",
   "cannotCmd": "You have already rated this product",
   "updateFailed": "Updating information failed",
   "notEmptyName": "Name cannot be left blank",
   "createBrandFailed": "Create Brand Failed",
   "onlyPngJpg": "You can only upload Png,Jpg file images",
   "smaller2MB": "Photos cannot exceed 2MB",
   "choosenBrand": "Please select Brand to edit",
   "createdItemFailed": "Creation failed. Please check again",
   "missingdataRequired": "Missing required information",
   "failed": "Failed",
   "cannotDelete": "Cannot be deleted anymore",
   "saveFailed": "Save failed",
   "choosenAllInfor": "Please select full information",
   "smaller1": "Cannot be smaller than 1",

   "addItemSuccess": "Added successfully",
   "deleteSuccess": "Delete successfully",
   "register": "Registered successfully",
   "addCartSuccess": "Successfully added product to cart",
   "updateSuccess": "Updated information successfully",
   "addCmt" :"Product review successful",
    "addCmtFailed" :"You have already rated this product",
   "update":"Update",
   "upload":"Upload",

   "newProduct":"New Product"
}
